robotnl/CheckOperator.py
robotnl/RobotChecks.py
robotnl/__init__.py
robotnl/inline_keywords.py
robotnl/version.py
robotframework_nl-3.1.0.dist-info/LICENSE
robotframework_nl-3.1.0.dist-info/METADATA
robotframework_nl-3.1.0.dist-info/WHEEL
robotframework_nl-3.1.0.dist-info/top_level.txt
robotframework_nl-3.1.0.dist-info/RECORD
