Metadata-Version: 2.1
Name: robotframework-nl
Version: 3.1.0
Summary: robotnl is a proving ground to boost Robot framework closer to Natural Language.
Author-email: Johan Foederer <github@famfoe.nl>
License: BSD 3-Clause License
Project-URL: Homepage, https://github.com/JFoederer/robotframeworkNL
Keywords: robotframework,robot,testing,dsl
Classifier: License :: OSI Approved :: BSD License
Classifier: Programming Language :: Python :: 3
Classifier: Operating System :: OS Independent
Requires-Python: >=3.8
License-File: LICENSE
Requires-Dist: robotframework >=7.0
